pengines/Builder.py
pengines/Exceptions.py
pengines/Pengine.py
pengines/Query.py
pengines/State.py
pengines/__init__.py
pengines-0.1.8.dist-info/METADATA
pengines-0.1.8.dist-info/RECORD
pengines-0.1.8.dist-info/WHEEL
pengines-0.1.8.dist-info/top_level.txt
