Metadata-Version: 2.1
Name: pengines
Version: 0.1.8
Summary: A simple python library for interacting with SWI-Prologs Pengines
Home-page: https://github.com/ian-andrich/PythonPengines
Author: Ian Andrich, Chris Mungall
Author-email: iandrich87+github@gmail.com
License: UNKNOWN
Download-URL: https://github.com/ian-andrich/PythonPengines/0.1.4
Keywords: pengines,pengine,prolog,swipl,swi-prolog,logic programming
Platform: UNKNOWN
